{"id":57404,"name":"Radiant Origins Store Championship","category":"store-championships","format":"standard","startAt":"2026-07-04T16:00:00.000Z","season":"RDO","host":{"name":"Axis","address":"Achrafieh Sassine Street AL Farah954 Building\nBeirut \nLebanon","country":"LB"},"playerCount":19,"swissRounds":5,"cutSize":0,"url":"https://omni.gatcg.com/events/57404","players":{"8498":"MystoganZero","14028":"Yupetro","24145":"Emperor","24393":"Avion26","24440":"Ihab86","24696":"Mega","24698":"Loppy","24699":"Redboy10","24701":"Whitewolf","25068":"SolInvictus92","25081":"Jeang98","25616":"Genevieve","25617":"Torq","28096":"NullVox","28682":"SleepyKn1ght","29580":"WarIsBad","29859":"NTR0P","29935":"Ghazzawi","30018":"CBM"},"standings":[{"rank":1,"player":8498,"wins":4,"losses":1,"ties":0,"score":12,"byes":0,"gwPercent":80,"mwPercent":80,"hasDeck":true,"status":"winner"},{"rank":2,"player":14028,"wins":4,"losses":1,"ties":0,"score":12,"byes":0,"gwPercent":77.778,"mwPercent":80,"hasDeck":true,"status":"eliminated"},{"rank":3,"player":28096,"wins":4,"losses":1,"ties":0,"score":12,"byes":0,"gwPercent":64.286,"mwPercent":80,"hasDeck":true,"status":"winner"},{"rank":4,"player":24696,"wins":3,"losses":0,"ties":2,"score":11,"byes":0,"gwPercent":75,"mwPercent":60,"hasDeck":true,"status":"winner"},{"rank":5,"player":24440,"wins":3,"losses":1,"ties":1,"score":10,"byes":0,"gwPercent":77.778,"mwPercent":60,"hasDeck":true,"status":"winner"},{"rank":6,"player":24701,"wins":3,"losses":2,"ties":0,"score":9,"byes":0,"gwPercent":53.846,"mwPercent":60,"hasDeck":true,"status":"winner"},{"rank":7,"player":25081,"wins":3,"losses":2,"ties":0,"score":9,"byes":0,"gwPercent":58.333,"mwPercent":60,"hasDeck":true,"status":"eliminated"},{"rank":8,"player":30018,"wins":3,"losses":2,"ties":0,"score":9,"byes":0,"gwPercent":60,"mwPercent":60,"hasDeck":true,"status":"winner"},{"rank":9,"player":24699,"wins":2,"losses":1,"ties":2,"score":8,"byes":0,"gwPercent":63.636,"mwPercent":40,"hasDeck":true,"status":"winner"},{"rank":10,"player":25068,"wins":2,"losses":1,"ties":2,"score":8,"byes":0,"gwPercent":55.556,"mwPercent":40,"hasDeck":true,"status":"eliminated"},{"rank":11,"player":24145,"wins":2,"losses":2,"ties":1,"score":7,"byes":0,"gwPercent":50,"mwPercent":40,"hasDeck":true,"status":"winner"},{"rank":12,"player":28682,"wins":2,"losses":2,"ties":1,"score":7,"byes":0,"gwPercent":44.444,"mwPercent":40,"hasDeck":true,"status":"eliminated"},{"rank":13,"player":24698,"wins":1,"losses":3,"ties":0,"score":6,"byes":1,"gwPercent":45.455,"mwPercent":25,"hasDeck":true,"status":"eliminated"},{"rank":14,"player":29935,"wins":1,"losses":3,"ties":0,"score":6,"byes":1,"gwPercent":28.571,"mwPercent":25,"hasDeck":true,"status":"eliminated"},{"rank":15,"player":29580,"wins":2,"losses":3,"ties":0,"score":6,"byes":0,"gwPercent":40,"mwPercent":40,"hasDeck":true,"status":"winner"},{"rank":16,"player":25617,"wins":0,"losses":3,"ties":1,"score":4,"byes":1,"gwPercent":12.5,"mwPercent":0,"hasDeck":true,"status":"eliminated"},{"rank":17,"player":24393,"wins":1,"losses":3,"ties":0,"score":3,"byes":0,"gwPercent":25,"mwPercent":25,"hasDeck":true,"status":"eliminated"},{"rank":18,"player":29859,"wins":0,"losses":4,"ties":0,"score":3,"byes":1,"gwPercent":0,"mwPercent":0,"hasDeck":true,"status":"eliminated"},{"rank":19,"player":25616,"wins":0,"losses":5,"ties":0,"score":0,"byes":0,"gwPercent":9.091,"mwPercent":0,"hasDeck":true,"status":"eliminated"}],"decklists":[{"player":8498,"material":[{"slug":"spirit-of-wind","name":"Spirit of Wind","qty":1},{"slug":"arisanna-herbalist-prodigy","name":"Arisanna, Herbalist Prodigy","qty":1},{"slug":"backup-charger","name":"Backup Charger","qty":1},{"slug":"censer-of-restful-peace","name":"Censer of Restful Peace","qty":1},{"slug":"essence-crucible","name":"Essence Crucible","qty":1},{"slug":"grand-crusaders-ring","name":"Grand Crusader's Ring","qty":1},{"slug":"ingredient-pouch","name":"Ingredient Pouch","qty":1},{"slug":"orb-of-sealing","name":"Orb of Sealing","qty":1},{"slug":"safeguard-amulet","name":"Safeguard Amulet","qty":1},{"slug":"tariff-ring","name":"Tariff Ring","qty":1},{"slug":"purifying-thurible","name":"Purifying Thurible","qty":1},{"slug":"nullifying-mirror","name":"Nullifying Mirror","qty":1}],"main":[{"slug":"bandit-gaze-leader","name":"Bandit, Gaze Leader","qty":4},{"slug":"distilled-water","name":"Distilled Water","qty":3},{"slug":"escape-the-wreckage","name":"Escape the Wreckage","qty":3},{"slug":"fluffy-shopkeep","name":"Fluffy Shopkeep","qty":2},{"slug":"protector-raccoon","name":"Protector Raccoon","qty":2},{"slug":"turbo-charge","name":"Turbo Charge","qty":2},{"slug":"unbroken-mustang","name":"Unbroken Mustang","qty":2},{"slug":"aesan-protector","name":"Aesan Protector","qty":3},{"slug":"calming-breeze","name":"Calming Breeze","qty":1},{"slug":"cyclical-breeze","name":"Cyclical Breeze","qty":3},{"slug":"dream-fairy","name":"Dream Fairy","qty":3},{"slug":"fairy-whispers","name":"Fairy Whispers","qty":4},{"slug":"innervate-agility","name":"Innervate Agility","qty":1},{"slug":"razorgale-calling","name":"Razorgale Calling","qty":4},{"slug":"reclaim","name":"Reclaim","qty":4},{"slug":"scout-the-land","name":"Scout the Land","qty":2},{"slug":"skirting-step","name":"Skirting Step","qty":2},{"slug":"speed-potion","name":"Speed Potion","qty":2},{"slug":"stifling-gyre","name":"Stifling Gyre","qty":1},{"slug":"three-visits","name":"Three Visits","qty":3},{"slug":"veiling-breeze","name":"Veiling Breeze","qty":4},{"slug":"windmill-engineer","name":"Windmill Engineer","qty":4},{"slug":"zephyr","name":"Zephyr","qty":2}],"sideboard":[{"slug":"calming-breeze","name":"Calming Breeze","qty":1},{"slug":"obscured-offering","name":"Obscured Offering","qty":1},{"slug":"fluffy-shopkeep","name":"Fluffy Shopkeep","qty":1},{"slug":"innervate-agility","name":"Innervate Agility","qty":1},{"slug":"stifling-gyre","name":"Stifling Gyre","qty":2},{"slug":"tempest-downfall","name":"Tempest Downfall","qty":2},{"slug":"spellshield-wind","name":"Spellshield: Wind","qty":2},{"slug":"ensnaring-fumes","name":"Ensnaring Fumes","qty":3},{"slug":"break-apart","name":"Break Apart","qty":2}]},{"player":14028,"material":[{"slug":"spirit-of-wind","name":"Spirit of Wind","qty":1},{"slug":"clarent-reimagined","name":"Clarent, Reimagined","qty":1},{"slug":"lorraine-blademaster","name":"Lorraine, Blademaster","qty":1},{"slug":"lorraine-spirit-ruler","name":"Lorraine, Spirit Ruler","qty":1},{"slug":"lorraine-wandering-warrior","name":"Lorraine, Wandering Warrior","qty":1},{"slug":"prismatic-edge","name":"Prismatic Edge","qty":1},{"slug":"purifying-thurible","name":"Purifying Thurible","qty":1},{"slug":"drawn-blade","name":"Drawn Blade","qty":1},{"slug":"clarent-sword-of-peace","name":"Clarent, Sword of Peace","qty":1},{"slug":"the-looking-glass","name":"The Looking Glass","qty":1},{"slug":"palvor-sword","name":"Palvor Sword","qty":1},{"slug":"inert-sword","name":"Inert Sword","qty":1}],"main":[{"slug":"benediction-angel","name":"Benediction Angel","qty":2},{"slug":"cheshire-cat-impish-grin","name":"Cheshire Cat, Impish Grin","qty":3},{"slug":"dungeon-guide","name":"Dungeon Guide","qty":4},{"slug":"escape-the-wreckage","name":"Escape the Wreckage","qty":1},{"slug":"fluffy-shopkeep","name":"Fluffy Shopkeep","qty":4},{"slug":"alizarin-longbowman","name":"Alizarin Longbowman","qty":1},{"slug":"chamberlain-toad","name":"Chamberlain Toad","qty":1},{"slug":"aella-zephyrs-hand","name":"Aella, Zephyr's Hand","qty":3},{"slug":"aesan-protector","name":"Aesan Protector","qty":3},{"slug":"beseech-the-winds","name":"Beseech the Winds","qty":2},{"slug":"calming-breeze","name":"Calming Breeze","qty":2},{"slug":"dream-fairy","name":"Dream Fairy","qty":2},{"slug":"fairy-whispers","name":"Fairy Whispers","qty":4},{"slug":"rally-the-peasants","name":"Rally the Peasants","qty":2},{"slug":"reclaim","name":"Reclaim","qty":4},{"slug":"scout-the-land","name":"Scout the Land","qty":2},{"slug":"stifling-trap","name":"Stifling Trap","qty":1},{"slug":"tempestuous-seraphim","name":"Tempestuous Seraphim","qty":2},{"slug":"veiling-breeze","name":"Veiling Breeze","qty":2},{"slug":"verdigris-decree","name":"Verdigris Decree","qty":1},{"slug":"windmill-engineer","name":"Windmill Engineer","qty":4},{"slug":"crux-sight","name":"Crux Sight","qty":1},{"slug":"ghosts-of-pendragon","name":"Ghosts of Pendragon","qty":4},{"slug":"numinous-monk","name":"Numinous Monk","qty":1},{"slug":"spirit-blade-ascension","name":"Spirit Blade: Ascension","qty":4}],"sideboard":[{"slug":"annul-spell","name":"Annul Spell","qty":3},{"slug":"blanche-sheltering-saint","name":"Blanche, Sheltering Saint","qty":2},{"slug":"dream-fairy","name":"Dream Fairy","qty":1},{"slug":"hurricane-sweep","name":"Hurricane Sweep","qty":2},{"slug":"scatter-essence","name":"Scatter Essence","qty":2},{"slug":"stifling-gyre","name":"Stifling Gyre","qty":2},{"slug":"stifling-trap","name":"Stifling Trap","qty":1},{"slug":"spirit-blade-retribution","name":"Spirit Blade: Retribution","qty":2}]},{"player":24145,"material":[{"slug":"spirit-of-slime","name":"Spirit of Slime","qty":1},{"slug":"silvie-wilds-whisperer","name":"Silvie, Wilds Whisperer","qty":1},{"slug":"silvie-with-the-pack","name":"Silvie, With the Pack","qty":1},{"slug":"silvie-slime-sovereign","name":"Silvie, Slime Sovereign","qty":1},{"slug":"verdant-scepter","name":"Verdant Scepter","qty":1},{"slug":"covenant-of-thorns","name":"Covenant of Thorns","qty":1},{"slug":"beastbond-paws","name":"Beastbond Paws","qty":1},{"slug":"viridian-protective-trinket","name":"Viridian Protective Trinket","qty":1},{"slug":"slime-totem","name":"Slime Totem","qty":1},{"slug":"stonescale-band","name":"Stonescale Band","qty":1},{"slug":"slime-nexus","name":"Slime Nexus","qty":1},{"slug":"key-slime-pudding","name":"Key Slime Pudding","qty":1}],"main":[{"slug":"gather-slimes","name":"Gather Slimes","qty":2},{"slug":"slime-eruption","name":"Slime Eruption","qty":3},{"slug":"baby-red-slime","name":"Baby Red Slime","qty":4},{"slug":"ethereal-slime","name":"Ethereal Slime","qty":4},{"slug":"storm-slime","name":"Storm Slime","qty":4},{"slug":"slimeshield","name":"Slimeshield","qty":3},{"slug":"slimes-blessing","name":"Slime's Blessing","qty":3},{"slug":"slimecall-cyclone","name":"Slimecall Cyclone","qty":3},{"slug":"slime-calling","name":"Slime Calling","qty":4},{"slug":"slime-swarm","name":"Slime Swarm","qty":4},{"slug":"blissful-calling","name":"Blissful Calling","qty":4},{"slug":"baby-gray-slime","name":"Baby Gray Slime","qty":4},{"slug":"baby-silver-slime","name":"Baby Silver Slime","qty":4},{"slug":"limitless-slime","name":"Limitless Slime","qty":4},{"slug":"forest-cake","name":"Forest Cake","qty":4},{"slug":"lustrous-slime","name":"Lustrous Slime","qty":2},{"slug":"escape-the-wreckage","name":"Escape the Wreckage","qty":1},{"slug":"dungeon-guide","name":"Dungeon Guide","qty":4}],"sideboard":[{"slug":"unbroken-mustang","name":"Unbroken Mustang","qty":3},{"slug":"nullifying-lantern","name":"Nullifying Lantern","qty":1},{"slug":"fire-resonance-bauble","name":"Fire Resonance Bauble","qty":1},{"slug":"water-resonance-bauble","name":"Water Resonance Bauble","qty":1},{"slug":"wind-resonance-bauble","name":"Wind Resonance Bauble","qty":1}]},{"player":24393,"material":[{"slug":"spirit-of-wind","name":"Spirit of Wind","qty":1},{"slug":"tariff-ring","name":"Tariff Ring","qty":1},{"slug":"lost-providence","name":"Lost Providence","qty":1},{"slug":"enfeebling-orb","name":"Enfeebling Orb","qty":1},{"slug":"gearstride-gloves","name":"Gearstride Gloves","qty":1},{"slug":"safeguard-amulet","name":"Safeguard Amulet","qty":1},{"slug":"windwalker-boots","name":"Windwalker Boots","qty":1},{"slug":"assassins-ripper","name":"Assassin's Ripper","qty":1},{"slug":"shadows-claw","name":"Shadow's Claw","qty":1},{"slug":"tristan-shadowdancer","name":"Tristan, Shadowdancer","qty":1},{"slug":"tristan-hired-blade","name":"Tristan, Hired Blade","qty":1},{"slug":"tristan-underhanded","name":"Tristan, Underhanded","qty":1}],"main":[{"slug":"slice-and-dice","name":"Slice and Dice","qty":3},{"slug":"mastermind-scheme","name":"Mastermind Scheme","qty":3},{"slug":"stifling-trap","name":"Stifling Trap","qty":3},{"slug":"surveil-the-winds","name":"Surveil the Winds","qty":4},{"slug":"reclaim","name":"Reclaim","qty":3},{"slug":"arrow-trap","name":"Arrow Trap","qty":2},{"slug":"ensnaring-fumes","name":"Ensnaring Fumes","qty":2},{"slug":"dream-fairy","name":"Dream Fairy","qty":2},{"slug":"veiling-breeze","name":"Veiling Breeze","qty":2},{"slug":"sadi-blood-harvester","name":"Sadi, Blood Harvester","qty":4},{"slug":"shadowstrike","name":"Shadowstrike","qty":3},{"slug":"zephyr","name":"Zephyr","qty":2},{"slug":"innervate-agility","name":"Innervate Agility","qty":1},{"slug":"windmill-engineer","name":"Windmill Engineer","qty":4},{"slug":"aesan-protector","name":"Aesan Protector","qty":3},{"slug":"aella-zephyrs-hand","name":"Aella, Zephyr's Hand","qty":1},{"slug":"dungeon-guide","name":"Dungeon Guide","qty":3},{"slug":"winbless-lookout","name":"Winbless Lookout","qty":4},{"slug":"fairy-whispers","name":"Fairy Whispers","qty":4},{"slug":"swift-recruit","name":"Swift Recruit","qty":2},{"slug":"scout-the-land","name":"Scout the Land","qty":1},{"slug":"incapacitate","name":"Incapacitate","qty":4}],"sideboard":[{"slug":"zephyr","name":"Zephyr","qty":1},{"slug":"sharpen-blade","name":"Sharpen Blade","qty":1},{"slug":"veiling-breeze","name":"Veiling Breeze","qty":1},{"slug":"ensnaring-fumes","name":"Ensnaring Fumes","qty":1},{"slug":"exploit-vulnerability","name":"Exploit Vulnerability","qty":2},{"slug":"dream-fairy","name":"Dream Fairy","qty":1},{"slug":"penumbral-waltz","name":"Penumbral Waltz","qty":1},{"slug":"unbroken-mustang","name":"Unbroken Mustang","qty":2},{"slug":"nullifying-lantern","name":"Nullifying Lantern","qty":1},{"slug":"scatter-essence","name":"Scatter Essence","qty":2}]},{"player":24440,"material":[{"slug":"spirit-of-wind","name":"Spirit of Wind","qty":1},{"slug":"guo-jia-chosen-disciple","name":"Guo Jia, Chosen Disciple","qty":1},{"slug":"guo-jia-blessed-scion","name":"Guo Jia, Blessed Scion","qty":1},{"slug":"guo-jia-heavens-favored","name":"Guo Jia, Heaven's Favored","qty":1},{"slug":"candlelight-hourglass","name":"Candlelight Hourglass","qty":1},{"slug":"censer-of-restful-peace","name":"Censer of Restful Peace","qty":1},{"slug":"enfeebling-orb","name":"Enfeebling Orb","qty":1},{"slug":"portentous-tanggu","name":"Portentous Tanggu","qty":1},{"slug":"nullifying-mirror","name":"Nullifying Mirror","qty":1},{"slug":"purifying-thurible","name":"Purifying Thurible","qty":1},{"slug":"fabled-azurite-fatestone","name":"Fabled Azurite Fatestone","qty":1},{"slug":"incandescent-reliquary","name":"Incandescent Reliquary","qty":1}],"main":[{"slug":"crystallized-destiny","name":"Crystallized Destiny","qty":1},{"slug":"dungeon-guide","name":"Dungeon Guide","qty":4},{"slug":"escape-the-wreckage","name":"Escape the Wreckage","qty":2},{"slug":"forest-cake","name":"Forest Cake","qty":2},{"slug":"aesan-protector","name":"Aesan Protector","qty":3},{"slug":"beseech-the-winds","name":"Beseech the Winds","qty":3},{"slug":"beseeched-fatestone","name":"Beseeched Fatestone","qty":2},{"slug":"brisk-windtrotter","name":"Brisk Windtrotter","qty":2},{"slug":"byakkos-command","name":"Byakko's Command","qty":4},{"slug":"displace","name":"Displace","qty":2},{"slug":"dream-fairy","name":"Dream Fairy","qty":3},{"slug":"fairy-whispers","name":"Fairy Whispers","qty":4},{"slug":"innervate-agility","name":"Innervate Agility","qty":2},{"slug":"reclaim","name":"Reclaim","qty":2},{"slug":"stifling-gyre","name":"Stifling Gyre","qty":2},{"slug":"stifling-trap","name":"Stifling Trap","qty":3},{"slug":"veiling-breeze","name":"Veiling Breeze","qty":2},{"slug":"windmill-engineer","name":"Windmill Engineer","qty":4},{"slug":"zephyr","name":"Zephyr","qty":4},{"slug":"harness-lightning","name":"Harness Lightning","qty":4},{"slug":"seiryuus-command","name":"Seiryuu's Command","qty":2},{"slug":"excalibur-cleansing-light","name":"Excalibur, Cleansing Light","qty":2},{"slug":"imperial-countermeasure","name":"Imperial Countermeasure","qty":2},{"slug":"annul-spell","name":"Annul Spell","qty":1},{"slug":"optical-control","name":"Optical Control","qty":1}],"sideboard":[{"slug":"annul-spell","name":"Annul Spell","qty":2},{"slug":"blanche-sheltering-saint","name":"Blanche, Sheltering Saint","qty":2},{"slug":"crystallized-destiny","name":"Crystallized Destiny","qty":1},{"slug":"resolute-stand","name":"Resolute Stand","qty":2},{"slug":"scatter-essence","name":"Scatter Essence","qty":2},{"slug":"optical-control","name":"Optical Control","qty":1},{"slug":"uther-illustrious-king","name":"Uther, Illustrious King","qty":2},{"slug":"tricastles-of-lucenia","name":"Tricastles of Lucenia","qty":2},{"slug":"fatestone-of-heaven","name":"Fatestone of Heaven","qty":1}]},{"player":24696,"material":[{"slug":"tariff-ring","name":"Tariff Ring","qty":1},{"slug":"tome-of-abyssal-heaven","name":"Tome of Abyssal Heaven","qty":1},{"slug":"safeguard-amulet","name":"Safeguard Amulet","qty":1},{"slug":"grand-crusaders-ring","name":"Grand Crusader's Ring","qty":1},{"slug":"prismspire-scepter","name":"Prismspire Scepter","qty":1},{"slug":"chalice-of-blood","name":"Chalice of Blood","qty":1},{"slug":"shuang-ji-of-sacrifice","name":"Shuang Ji of Sacrifice","qty":1},{"slug":"berserker-plate","name":"Berserker Plate","qty":1},{"slug":"jin-undying-resolve","name":"Jin, Undying Resolve","qty":1},{"slug":"jin-zealous-maverick","name":"Jin, Zealous Maverick","qty":1},{"slug":"jin-fate-defiant","name":"Jin, Fate Defiant","qty":1},{"slug":"spirit-of-serene-fire","name":"Spirit of Serene Fire","qty":1}],"main":[{"slug":"cremation-ritual","name":"Cremation Ritual","qty":3},{"slug":"regenerate","name":"Regenerate","qty":4},{"slug":"mend-flesh","name":"Mend Flesh","qty":4},{"slug":"heavenly-guide","name":"Heavenly Guide","qty":2},{"slug":"incapacitate","name":"Incapacitate","qty":2},{"slug":"relentless-outburst","name":"Relentless Outburst","qty":2},{"slug":"creative-shock","name":"Creative Shock","qty":3},{"slug":"hemorrhaging-rend","name":"Hemorrhaging Rend","qty":4},{"slug":"dungeon-guide","name":"Dungeon Guide","qty":4},{"slug":"crimson-rupture","name":"Crimson Rupture","qty":1},{"slug":"seething-intercession","name":"Seething Intercession","qty":1},{"slug":"clumsy-apprentice","name":"Clumsy Apprentice","qty":2},{"slug":"angel-attendant","name":"Angel Attendant","qty":4},{"slug":"flagrant-guide","name":"Flagrant Guide","qty":2},{"slug":"stalwart-shieldmate","name":"Stalwart Shieldmate","qty":4},{"slug":"bloodshroud-temper","name":"Bloodshroud Temper","qty":2},{"slug":"enrage","name":"Enrage","qty":3},{"slug":"transfusive-aura","name":"Transfusive Aura","qty":2},{"slug":"obscured-offering","name":"Obscured Offering","qty":2},{"slug":"polearmed-steed","name":"Pole-armed Steed","qty":2},{"slug":"proof-of-life","name":"Proof of Life","qty":1},{"slug":"bloodbond-bladesworn","name":"Bloodbond Bladesworn","qty":2},{"slug":"benediction-angel","name":"Benediction Angel","qty":4},{"slug":"smoke-out","name":"Smoke Out","qty":2},{"slug":"crimson-prescience","name":"Crimson Prescience","qty":1}],"sideboard":[{"slug":"crimson-rupture","name":"Crimson Rupture","qty":2},{"slug":"spellward-scepter","name":"Spellward Scepter","qty":1},{"slug":"siphoning-stab","name":"Siphoning Stab","qty":2},{"slug":"coronation-ceremony","name":"Coronation Ceremony","qty":2},{"slug":"varuckan-acolyte","name":"Varuckan Acolyte","qty":2},{"slug":"deflecting-advantage","name":"Deflecting Advantage","qty":2},{"slug":"lavastorm","name":"Lavastorm","qty":1},{"slug":"expel-the-departed","name":"Expel the Departed","qty":1}]},{"player":24698,"material":[{"slug":"spirit-of-fire","name":"Spirit of Fire","qty":1},{"slug":"guo-jia-chosen-disciple","name":"Guo Jia, Chosen Disciple","qty":1},{"slug":"fabled-ruby-fatestone","name":"Fabled Ruby Fatestone","qty":1},{"slug":"smoke-bombs","name":"Smoke Bombs","qty":1},{"slug":"portentous-tanggu","name":"Portentous Tanggu","qty":1},{"slug":"fire-resonance-bauble","name":"Fire Resonance Bauble","qty":1},{"slug":"wind-resonance-bauble","name":"Wind Resonance Bauble","qty":1},{"slug":"water-resonance-bauble","name":"Water Resonance Bauble","qty":1},{"slug":"impact-hammer","name":"Impact Hammer","qty":1},{"slug":"enfeebling-orb","name":"Enfeebling Orb","qty":1},{"slug":"censer-of-restful-peace","name":"Censer of Restful Peace","qty":1},{"slug":"tariff-ring","name":"Tariff Ring","qty":1}],"main":[{"slug":"restorative-flame","name":"Restorative Flame","qty":2},{"slug":"spark-alight","name":"Spark Alight","qty":2},{"slug":"intensified-pyre","name":"Intensified Pyre","qty":2},{"slug":"embercrypt-burn","name":"Embercrypt Burn","qty":2},{"slug":"suzakus-command","name":"Suzaku's Command","qty":4},{"slug":"ignite-the-soul","name":"Ignite the Soul","qty":2},{"slug":"lavaplume-fatestone","name":"Lavaplume Fatestone","qty":4},{"slug":"demolition","name":"Demolition","qty":3},{"slug":"smoke-out","name":"Smoke Out","qty":2},{"slug":"coiled-fatestone","name":"Coiled Fatestone","qty":2},{"slug":"cinder-geyser","name":"Cinder Geyser","qty":2},{"slug":"peppered-chef","name":"Peppered Chef","qty":4},{"slug":"crystallized-destiny","name":"Crystallized Destiny","qty":2},{"slug":"vermilion-decree","name":"Vermilion Decree","qty":4},{"slug":"searing-truth","name":"Searing Truth","qty":4},{"slug":"avatar-of-suzaku","name":"Avatar of Suzaku","qty":4},{"slug":"creative-shock","name":"Creative Shock","qty":3},{"slug":"gilded-pyre","name":"Gilded Pyre","qty":2},{"slug":"ignite-fate","name":"Ignite Fate","qty":1},{"slug":"heated-vengeance","name":"Heated Vengeance","qty":3},{"slug":"fiery-interference","name":"Fiery Interference","qty":3},{"slug":"broken-promises","name":"Broken Promises","qty":1},{"slug":"blazing-throw","name":"Blazing Throw","qty":2},{"slug":"shatter-the-brittle","name":"Shatter the Brittle","qty":2}],"sideboard":[{"slug":"ignis-deus","name":"Ignis Deus","qty":2},{"slug":"gilded-pyre","name":"Gilded Pyre","qty":1},{"slug":"flamewreath-call","name":"Flamewreath Call","qty":1},{"slug":"spark-alight","name":"Spark Alight","qty":1},{"slug":"restorative-flame","name":"Restorative Flame","qty":1},{"slug":"surging-bolt","name":"Surging Bolt","qty":2},{"slug":"heated-vengeance","name":"Heated Vengeance","qty":1},{"slug":"safeguard-amulet","name":"Safeguard Amulet","qty":1},{"slug":"bauble-of-abundance","name":"Bauble of Abundance","qty":1}]},{"player":24699,"material":[{"slug":"spirit-of-serene-fire","name":"Spirit of Serene Fire","qty":1},{"slug":"jin-fate-defiant","name":"Jin, Fate Defiant","qty":1},{"slug":"jin-zealous-maverick","name":"Jin, Zealous Maverick","qty":1},{"slug":"jin-undying-resolve","name":"Jin, Undying Resolve","qty":1},{"slug":"shuang-ji-of-sacrifice","name":"Shuang Ji of Sacrifice","qty":1},{"slug":"berserker-plate","name":"Berserker Plate","qty":1},{"slug":"tome-of-abyssal-heaven","name":"Tome of Abyssal Heaven","qty":1},{"slug":"chalice-of-blood","name":"Chalice of Blood","qty":1},{"slug":"grand-crusaders-ring","name":"Grand Crusader's Ring","qty":1},{"slug":"safeguard-amulet","name":"Safeguard Amulet","qty":1},{"slug":"spellward-scepter","name":"Spellward Scepter","qty":1},{"slug":"spirit-of-fire","name":"Spirit of Fire","qty":1}],"main":[{"slug":"dungeon-guide","name":"Dungeon Guide","qty":4},{"slug":"flagrant-guide","name":"Flagrant Guide","qty":4},{"slug":"benediction-angel","name":"Benediction Angel","qty":4},{"slug":"creative-shock","name":"Creative Shock","qty":4},{"slug":"library-witch","name":"Library Witch","qty":3},{"slug":"polearmed-steed","name":"Pole-armed Steed","qty":2},{"slug":"hasty-messenger","name":"Hasty Messenger","qty":3},{"slug":"cremation-ritual","name":"Cremation Ritual","qty":3},{"slug":"incapacitate","name":"Incapacitate","qty":2},{"slug":"regenerate","name":"Regenerate","qty":3},{"slug":"mend-flesh","name":"Mend Flesh","qty":4},{"slug":"enrage","name":"Enrage","qty":4},{"slug":"seething-intercession","name":"Seething Intercession","qty":2},{"slug":"exia-sight","name":"Exia Sight","qty":3},{"slug":"transfusive-aura","name":"Transfusive Aura","qty":3},{"slug":"proof-of-life","name":"Proof of Life","qty":1},{"slug":"relentless-outburst","name":"Relentless Outburst","qty":1},{"slug":"fast-cure","name":"Fast Cure","qty":3},{"slug":"hemorrhaging-rend","name":"Hemorrhaging Rend","qty":3},{"slug":"bloodshroud-temper","name":"Bloodshroud Temper","qty":2},{"slug":"bloodbond-bladesworn","name":"Bloodbond Bladesworn","qty":1},{"slug":"limitless-defiance","name":"Limitless Defiance","qty":1}],"sideboard":[{"slug":"crimson-prescience","name":"Crimson Prescience","qty":3},{"slug":"annihilation","name":"Annihilation","qty":1},{"slug":"varuckan-acolyte","name":"Varuckan Acolyte","qty":3},{"slug":"lavastorm","name":"Lavastorm","qty":1},{"slug":"bloodshroud-temper","name":"Bloodshroud Temper","qty":1},{"slug":"crimson-rupture","name":"Crimson Rupture","qty":2},{"slug":"transfusive-aura","name":"Transfusive Aura","qty":1},{"slug":"proof-of-life","name":"Proof of Life","qty":1},{"slug":"bloodseeker-magus","name":"Bloodseeker Magus","qty":2}]},{"player":24701,"material":[{"slug":"spirit-of-fire","name":"Spirit of Fire","qty":1},{"slug":"silvie-with-the-pack","name":"Silvie, With the Pack","qty":1},{"slug":"silvie-wilds-whisperer","name":"Silvie, Wilds Whisperer","qty":1},{"slug":"silvie-slime-sovereign","name":"Silvie, Slime Sovereign","qty":1},{"slug":"lost-providence","name":"Lost Providence","qty":1},{"slug":"backup-charger","name":"Backup Charger","qty":1},{"slug":"beastbond-boots","name":"Beastbond Boots","qty":1},{"slug":"covenant-of-thorns","name":"Covenant of Thorns","qty":1},{"slug":"gaias-blessing","name":"Gaia's Blessing","qty":1},{"slug":"stonescale-band","name":"Stonescale Band","qty":1},{"slug":"horn-of-beastcalling","name":"Horn of Beastcalling","qty":1},{"slug":"nullifying-mirror","name":"Nullifying Mirror","qty":1}],"main":[{"slug":"storm-slime","name":"Storm Slime","qty":4},{"slug":"dungeon-guide","name":"Dungeon Guide","qty":4},{"slug":"baby-red-slime","name":"Baby Red Slime","qty":4},{"slug":"creative-shock","name":"Creative Shock","qty":4},{"slug":"baby-silver-slime","name":"Baby Silver Slime","qty":4},{"slug":"slime-eruption","name":"Slime Eruption","qty":4},{"slug":"limitless-slime","name":"Limitless Slime","qty":4},{"slug":"ethereal-slime","name":"Ethereal Slime","qty":3},{"slug":"cremation-ritual","name":"Cremation Ritual","qty":4},{"slug":"baby-gray-slime","name":"Baby Gray Slime","qty":4},{"slug":"lustrous-slime","name":"Lustrous Slime","qty":2},{"slug":"undeniable-truth","name":"Undeniable Truth","qty":2},{"slug":"ghastly-slime","name":"Ghastly Slime","qty":1},{"slug":"gaias-songbird","name":"Gaia's Songbird","qty":2},{"slug":"slime-king","name":"Slime King","qty":1},{"slug":"escape-the-wreckage","name":"Escape the Wreckage","qty":2},{"slug":"topsy-decree","name":"Topsy Decree","qty":1},{"slug":"turbo-charge","name":"Turbo Charge","qty":1},{"slug":"hymn-of-gaias-grace","name":"Hymn of Gaia's Grace","qty":2},{"slug":"liminal-guide","name":"Liminal Guide","qty":2},{"slug":"red-slime","name":"Red Slime","qty":2},{"slug":"unbroken-mustang","name":"Unbroken Mustang","qty":1},{"slug":"fiery-interference","name":"Fiery Interference","qty":2},{"slug":"regal-inquisition","name":"Regal Inquisition","qty":1}],"sideboard":[{"slug":"resolute-stand","name":"Resolute Stand","qty":1},{"slug":"expel-the-departed","name":"Expel the Departed","qty":3},{"slug":"crystallized-destiny","name":"Crystallized Destiny","qty":1},{"slug":"crumbling-reign","name":"Crumbling Reign","qty":2},{"slug":"annul-spell","name":"Annul Spell","qty":2},{"slug":"quicksilver-grail","name":"Quicksilver Grail","qty":1},{"slug":"blanche-sheltering-saint","name":"Blanche, Sheltering Saint","qty":1},{"slug":"twilight-slime","name":"Twilight Slime","qty":2}]},{"player":25068,"material":[{"slug":"spirit-of-wind","name":"Spirit of Wind","qty":1},{"slug":"tristan-underhanded","name":"Tristan, Underhanded","qty":1},{"slug":"tristan-hired-blade","name":"Tristan, Hired Blade","qty":1},{"slug":"tristan-shadowreaver","name":"Tristan, Shadowreaver","qty":1},{"slug":"tristan-shadowdancer","name":"Tristan, Shadowdancer","qty":1},{"slug":"assassins-ripper","name":"Assassin's Ripper","qty":1},{"slug":"shadows-claw","name":"Shadow's Claw","qty":1},{"slug":"windwalker-boots","name":"Windwalker Boots","qty":1},{"slug":"censer-of-restful-peace","name":"Censer of Restful Peace","qty":1},{"slug":"backup-charger","name":"Backup Charger","qty":1},{"slug":"purifying-thurible","name":"Purifying Thurible","qty":1},{"slug":"tariff-ring","name":"Tariff Ring","qty":1}],"main":[{"slug":"hexbound-blade","name":"Hexbound Blade","qty":1},{"slug":"dream-fairy","name":"Dream Fairy","qty":2},{"slug":"incapacitate","name":"Incapacitate","qty":4},{"slug":"winbless-lookout","name":"Winbless Lookout","qty":4},{"slug":"surveil-the-winds","name":"Surveil the Winds","qty":4},{"slug":"mastermind-scheme","name":"Mastermind Scheme","qty":2},{"slug":"reclaim","name":"Reclaim","qty":4},{"slug":"ensnaring-fumes","name":"Ensnaring Fumes","qty":2},{"slug":"sadi-blood-harvester","name":"Sadi, Blood Harvester","qty":3},{"slug":"slice-and-dice","name":"Slice and Dice","qty":3},{"slug":"innervate-agility","name":"Innervate Agility","qty":2},{"slug":"calming-breeze","name":"Calming Breeze","qty":1},{"slug":"veiling-breeze","name":"Veiling Breeze","qty":3},{"slug":"fairy-whispers","name":"Fairy Whispers","qty":3},{"slug":"shadowstrike","name":"Shadowstrike","qty":3},{"slug":"aesan-protector","name":"Aesan Protector","qty":3},{"slug":"windmill-engineer","name":"Windmill Engineer","qty":4},{"slug":"dungeon-guide","name":"Dungeon Guide","qty":3},{"slug":"spirelle-schwartz-queen","name":"Spirelle, Schwartz Queen","qty":1},{"slug":"stifling-trap","name":"Stifling Trap","qty":3},{"slug":"zephyr","name":"Zephyr","qty":2},{"slug":"aella-zephyrs-hand","name":"Aella, Zephyr's Hand","qty":2},{"slug":"turbo-charge","name":"Turbo Charge","qty":1},{"slug":"stifling-gyre","name":"Stifling Gyre","qty":2}],"sideboard":[{"slug":"scatter-essence","name":"Scatter Essence","qty":2},{"slug":"verdigris-decree","name":"Verdigris Decree","qty":2},{"slug":"psychopomps-gale","name":"Psychopomp's Gale","qty":1},{"slug":"ensnaring-fumes","name":"Ensnaring Fumes","qty":2},{"slug":"eternal-magistrate","name":"Eternal Magistrate","qty":2},{"slug":"dream-fairy","name":"Dream Fairy","qty":2},{"slug":"innervate-agility","name":"Innervate Agility","qty":1},{"slug":"spellshield-wind","name":"Spellshield: Wind","qty":2},{"slug":"exploit-vulnerability","name":"Exploit Vulnerability","qty":1}]},{"player":25081,"material":[{"slug":"spirit-of-water","name":"Spirit of Water","qty":1},{"slug":"diana-aether-dilettante","name":"Diana, Aether Dilettante","qty":1},{"slug":"diana-judgments-arrow","name":"Diana, Judgment's Arrow","qty":1},{"slug":"flash-grenade","name":"Flash Grenade","qty":1},{"slug":"quicksilver-grail","name":"Quicksilver Grail","qty":1},{"slug":"quickstep-treads","name":"Quickstep Treads","qty":1},{"slug":"seekers-aetherwing","name":"Seeker's Aetherwing","qty":1},{"slug":"smoke-bombs","name":"Smoke Bombs","qty":1},{"slug":"aquamirage-whisper","name":"Aquamirage Whisper","qty":1},{"slug":"manas-cascade","name":"Mana's Cascade","qty":1},{"slug":"enfeebling-orb","name":"Enfeebling Orb","qty":1},{"slug":"ranger-boots","name":"Ranger Boots","qty":1}],"main":[{"slug":"aetheric-calibration","name":"Aetheric Calibration","qty":4},{"slug":"alacritous-huntress","name":"Alacritous Huntress","qty":1},{"slug":"nimble-longbowman","name":"Nimble Longbowman","qty":1},{"slug":"backstep","name":"Backstep","qty":4},{"slug":"charge-the-soul","name":"Charge the Soul","qty":4},{"slug":"prudent-nock","name":"Prudent Nock","qty":4},{"slug":"reposition","name":"Reposition","qty":3},{"slug":"take-aim","name":"Take Aim","qty":2},{"slug":"drown-in-aether","name":"Drown in Aether","qty":2},{"slug":"cerulean-decree","name":"Cerulean Decree","qty":1},{"slug":"engulf","name":"Engulf","qty":1},{"slug":"fracturize","name":"Fracturize","qty":4},{"slug":"frostbind","name":"Frostbind","qty":2},{"slug":"frostsworn-paladin","name":"Frostsworn Paladin","qty":4},{"slug":"frozen-dismissal","name":"Frozen Dismissal","qty":2},{"slug":"krustallan-archer","name":"Krustallan Archer","qty":4},{"slug":"refreshing-charge","name":"Refreshing Charge","qty":2},{"slug":"snow-white-weiss-queen","name":"Snow White, Weiss Queen","qty":2},{"slug":"tactical-retreat","name":"Tactical Retreat","qty":4},{"slug":"undercurrent-vantage","name":"Undercurrent Vantage","qty":3},{"slug":"weaving-manastream","name":"Weaving Manastream","qty":4},{"slug":"cell-sharpshooter","name":"Cell Sharpshooter","qty":2}],"sideboard":[{"slug":"nullifying-lantern","name":"Nullifying Lantern","qty":1},{"slug":"nullifying-mirror","name":"Nullifying Mirror","qty":1},{"slug":"overlapping-visages","name":"Overlapping Visages","qty":2},{"slug":"drown-in-aether","name":"Drown in Aether","qty":1},{"slug":"shademist-priestess","name":"Shademist Priestess","qty":1},{"slug":"snow-fairy","name":"Snow Fairy","qty":2},{"slug":"morgan-soul-guide","name":"Morgan, Soul Guide","qty":2},{"slug":"take-aim","name":"Take Aim","qty":1}]},{"player":25616,"material":[{"slug":"spirit-of-water","name":"Spirit of Water","qty":1},{"slug":"merlin-memorite-vassal","name":"Merlin, Memorite Vassal","qty":1},{"slug":"merlin-amethysts-glow","name":"Merlin, Amethyst's Glow","qty":1},{"slug":"merlin-brilliant-vestige","name":"Merlin, Brilliant Vestige","qty":1},{"slug":"prismspire-scepter","name":"Prismspire Scepter","qty":1},{"slug":"assassins-mantle","name":"Assassin's Mantle","qty":1},{"slug":"tariff-ring","name":"Tariff Ring","qty":1},{"slug":"assassins-ripper","name":"Assassin's Ripper","qty":1},{"slug":"poisoned-dagger","name":"Poisoned Dagger","qty":1},{"slug":"shardforged-blade","name":"Shardforged Blade","qty":1},{"slug":"inert-sword","name":"Inert Sword","qty":1},{"slug":"the-looking-glass","name":"The Looking Glass","qty":1}],"main":[{"slug":"spirit-blade-terminus","name":"Spirit Blade: Terminus","qty":4},{"slug":"crux-sight","name":"Crux Sight","qty":1},{"slug":"iridescent-resurgence","name":"Iridescent Resurgence","qty":1},{"slug":"numinous-monk","name":"Numinous Monk","qty":1},{"slug":"crossroads-specter","name":"Crossroads Specter","qty":1},{"slug":"dualitys-convergence","name":"Duality's Convergence","qty":4},{"slug":"materialize-the-soul","name":"Materialize the Soul","qty":4},{"slug":"spirits-blessing","name":"Spirit's Blessing","qty":1},{"slug":"intangible-geist","name":"Intangible Geist","qty":1},{"slug":"possessed-reaping","name":"Possessed Reaping","qty":2},{"slug":"protect-her-at-all-costs","name":"Protect Her At All Costs","qty":4},{"slug":"sparkling-adornment","name":"Sparkling Adornment","qty":1},{"slug":"crystallized-destiny","name":"Crystallized Destiny","qty":1},{"slug":"excalibur-reflected-edge","name":"Excalibur, Reflected Edge","qty":3},{"slug":"cheshire-cat-impish-grin","name":"Cheshire Cat, Impish Grin","qty":3},{"slug":"regal-inquisition","name":"Regal Inquisition","qty":2},{"slug":"dormouse-informant","name":"Dormouse Informant","qty":2},{"slug":"crystalline-reality","name":"Crystalline Reality","qty":1},{"slug":"vanish-from-sight","name":"Vanish from Sight","qty":1},{"slug":"conceal","name":"Conceal","qty":1},{"slug":"guerrilla-advantage","name":"Guerrilla Advantage","qty":1},{"slug":"frostsworn-paladin","name":"Frostsworn Paladin","qty":4},{"slug":"snow-white-weiss-queen","name":"Snow White, Weiss Queen","qty":1},{"slug":"water-barrier","name":"Water Barrier","qty":1},{"slug":"pearled-prayer","name":"Pearled Prayer","qty":1},{"slug":"fracturize","name":"Fracturize","qty":4},{"slug":"freeze-stiff","name":"Freeze Stiff","qty":1},{"slug":"spalling-cleanse","name":"Spalling Cleanse","qty":1},{"slug":"shademist-priestess","name":"Shademist Priestess","qty":1},{"slug":"condemning-evisceration","name":"Condemning Evisceration","qty":1},{"slug":"quiet-refraction","name":"Quiet Refraction","qty":2},{"slug":"will-to-save","name":"Will to Save","qty":2},{"slug":"drifting-rogue","name":"Drifting Rogue","qty":1},{"slug":"revitalizing-cleanse","name":"Revitalizing Cleanse","qty":2},{"slug":"seep-into-the-mind","name":"Seep Into the Mind","qty":2},{"slug":"stand-before-the-queen","name":"Stand Before the Queen","qty":2}],"sideboard":[{"slug":"fire-resonance-bauble","name":"Fire Resonance Bauble","qty":1},{"slug":"wind-resonance-bauble","name":"Wind Resonance Bauble","qty":1},{"slug":"converge-reflections","name":"Converge Reflections","qty":4},{"slug":"undeniable-truth","name":"Undeniable Truth","qty":4}]},{"player":25617,"material":[{"slug":"spirit-of-wind","name":"Spirit of Wind","qty":1},{"slug":"diana-keen-huntress","name":"Diana, Keen Huntress","qty":1},{"slug":"diana-deadly-duelist","name":"Diana, Deadly Duelist","qty":1},{"slug":"diana-duskstalker","name":"Diana, Duskstalker","qty":1},{"slug":"bauble-of-abundance","name":"Bauble of Abundance","qty":1},{"slug":"blights-ring","name":"Blight's Ring","qty":1},{"slug":"plated-bullet","name":"Plated Bullet","qty":1},{"slug":"tasershot","name":"Tasershot","qty":1},{"slug":"punishing-cartridge","name":"Punishing Cartridge","qty":1},{"slug":"seekers-rifle","name":"Seeker's Rifle","qty":1},{"slug":"blastshot-pump","name":"Blastshot Pump","qty":1},{"slug":"shadows-twin","name":"Shadow's Twin","qty":1}],"main":[{"slug":"beseech-the-winds","name":"Beseech the Winds","qty":1},{"slug":"fairy-whispers","name":"Fairy Whispers","qty":4},{"slug":"windmill-engineer","name":"Windmill Engineer","qty":1},{"slug":"reconnaissance-scout","name":"Reconnaissance Scout","qty":2},{"slug":"skirting-step","name":"Skirting Step","qty":4},{"slug":"concealed-marksman","name":"Concealed Marksman","qty":4},{"slug":"veiling-breeze","name":"Veiling Breeze","qty":3},{"slug":"reclaim","name":"Reclaim","qty":4},{"slug":"swift-recruit","name":"Swift Recruit","qty":4},{"slug":"take-cover","name":"Take Cover","qty":4},{"slug":"imperial-rifleman","name":"Imperial Rifleman","qty":4},{"slug":"supply-drone","name":"Supply Drone","qty":2},{"slug":"evasive-maneuvers","name":"Evasive Maneuvers","qty":4},{"slug":"take-aim","name":"Take Aim","qty":3},{"slug":"stifling-trap","name":"Stifling Trap","qty":4},{"slug":"reposition","name":"Reposition","qty":3},{"slug":"backstep","name":"Backstep","qty":4},{"slug":"materialize-munitions","name":"Materialize Munitions","qty":4},{"slug":"aesan-protector","name":"Aesan Protector","qty":3},{"slug":"umbral-tithe","name":"Umbral Tithe","qty":3},{"slug":"violet-haze","name":"Violet Haze","qty":1},{"slug":"dream-fairy","name":"Dream Fairy","qty":2},{"slug":"umbra-sight","name":"Umbra Sight","qty":2},{"slug":"dungeon-guide","name":"Dungeon Guide","qty":4},{"slug":"spellshield-wind","name":"Spellshield: Wind","qty":2},{"slug":"rapid-reload","name":"Rapid Reload","qty":1}],"sideboard":[{"slug":"fire-resonance-bauble","name":"Fire Resonance Bauble","qty":1},{"slug":"wind-resonance-bauble","name":"Wind Resonance Bauble","qty":1},{"slug":"flash-grenade","name":"Flash Grenade","qty":1},{"slug":"zephyr","name":"Zephyr","qty":4},{"slug":"dodge-roll","name":"Dodge Roll","qty":1},{"slug":"peer-beyond","name":"Peer Beyond","qty":1},{"slug":"bladed-riftseer","name":"Bladed Riftseer","qty":1}]},{"player":28096,"material":[{"slug":"spirit-of-fire","name":"Spirit of Fire","qty":1},{"slug":"ciel-loyal-valet","name":"Ciel, Loyal Valet","qty":1},{"slug":"ciel-mirages-grave","name":"Ciel, Mirage's Grave","qty":1},{"slug":"ciel-omenbringer","name":"Ciel, Omenbringer","qty":1},{"slug":"chalice-of-blood","name":"Chalice of Blood","qty":1},{"slug":"grande-sonnerie","name":"Grande Sonnerie","qty":1},{"slug":"devouring-malice","name":"Devouring Malice","qty":1},{"slug":"manxome-armoire","name":"Manxome Armoire","qty":1},{"slug":"lost-providence","name":"Lost Providence","qty":1},{"slug":"backup-charger","name":"Backup Charger","qty":1},{"slug":"folded-shadows","name":"Folded Shadows","qty":1},{"slug":"ducal-seal","name":"Ducal Seal","qty":1}],"main":[{"slug":"feu-awakening","name":"Feu Awakening","qty":4},{"slug":"library-witch","name":"Library Witch","qty":4},{"slug":"angel-attendant","name":"Angel Attendant","qty":4},{"slug":"resolute-stand","name":"Resolute Stand","qty":2},{"slug":"baleful-oblation","name":"Baleful Oblation","qty":4},{"slug":"advent-of-the-stormcaller","name":"Advent of the Stormcaller","qty":4},{"slug":"rictus-tiding","name":"Rictus Tiding","qty":3},{"slug":"cremation-ritual","name":"Cremation Ritual","qty":4},{"slug":"creative-shock","name":"Creative Shock","qty":4},{"slug":"ionized-asceticism","name":"Ionized Asceticism","qty":3},{"slug":"dungeon-guide","name":"Dungeon Guide","qty":4},{"slug":"under-fire","name":"Under Fire","qty":2},{"slug":"abnegation","name":"Abnegation","qty":2},{"slug":"turbo-charge","name":"Turbo Charge","qty":2},{"slug":"angelic-channeling","name":"Angelic Channeling","qty":3},{"slug":"undeniable-truth","name":"Undeniable Truth","qty":2},{"slug":"devastating-blow","name":"Devastating Blow","qty":2},{"slug":"extorting-blackjack","name":"Extorting Blackjack","qty":2},{"slug":"umbra-sight","name":"Umbra Sight","qty":2},{"slug":"fluffy-shopkeep","name":"Fluffy Shopkeep","qty":1},{"slug":"annul-spell","name":"Annul Spell","qty":2}],"sideboard":[{"slug":"regal-inquisition","name":"Regal Inquisition","qty":2},{"slug":"crystallized-destiny","name":"Crystallized Destiny","qty":1},{"slug":"fiery-interference","name":"Fiery Interference","qty":2},{"slug":"blanche-sheltering-saint","name":"Blanche, Sheltering Saint","qty":1},{"slug":"spirelle-schwartz-queen","name":"Spirelle, Schwartz Queen","qty":2},{"slug":"varuckan-acolyte","name":"Varuckan Acolyte","qty":2},{"slug":"resolute-stand","name":"Resolute Stand","qty":2},{"slug":"nocturnes-oblivion","name":"Nocturne's Oblivion","qty":1},{"slug":"reduce-to-ash","name":"Reduce to Ash","qty":2}]},{"player":28682,"material":[{"slug":"flawless-spirit-of-mordred","name":"Flawless Spirit of Mordred","qty":1},{"slug":"drawn-blade","name":"Drawn Blade","qty":1},{"slug":"scepter-of-lumina","name":"Scepter of Lumina","qty":1},{"slug":"mordred-burnished-avenger","name":"Mordred, Burnished Avenger","qty":1},{"slug":"mordred-flawless-blade","name":"Mordred, Flawless Blade","qty":1},{"slug":"mordred-fated-luminary","name":"Mordred, Fated Luminary","qty":1},{"slug":"tariff-ring","name":"Tariff Ring","qty":1},{"slug":"dummy-trainer","name":"Dummy Trainer","qty":1},{"slug":"mordred-aurelian-regent","name":"Mordred, Aurelian Regent","qty":1},{"slug":"safeguard-amulet","name":"Safeguard Amulet","qty":1},{"slug":"teardrop-diadem","name":"Teardrop Diadem","qty":1},{"slug":"rhongomiant-groves-spire","name":"Rhongomiant, Grove's Spire","qty":1}],"main":[{"slug":"thronekeeper-bullfrog","name":"Throne-Keeper Bullfrog","qty":3},{"slug":"water-barrier","name":"Water Barrier","qty":3},{"slug":"sudden-steel","name":"Sudden Steel","qty":2},{"slug":"dungeon-guide","name":"Dungeon Guide","qty":4},{"slug":"song-of-frost","name":"Song of Frost","qty":2},{"slug":"gentle-respite","name":"Gentle Respite","qty":3},{"slug":"fractal-of-waves","name":"Fractal of Waves","qty":4},{"slug":"dauntless-assault","name":"Dauntless Assault","qty":4},{"slug":"excalibur-cleansing-light","name":"Excalibur, Cleansing Light","qty":2},{"slug":"striking-tides","name":"Striking Tides","qty":2},{"slug":"refracting-missile","name":"Refracting Missile","qty":2},{"slug":"fracturize","name":"Fracturize","qty":4},{"slug":"warrior-of-the-fae-realm","name":"Warrior of the Fae Realm","qty":3},{"slug":"imperial-countermeasure","name":"Imperial Countermeasure","qty":3},{"slug":"gildas-faesworn-monarch","name":"Gildas, Faesworn Monarch","qty":3},{"slug":"snow-fairy","name":"Snow Fairy","qty":2},{"slug":"engulf","name":"Engulf","qty":1},{"slug":"fractal-of-rain","name":"Fractal of Rain","qty":4},{"slug":"regulus-blitz","name":"Regulus Blitz","qty":3},{"slug":"luminescent-slash","name":"Luminescent Slash","qty":2},{"slug":"frostsworn-paladin","name":"Frostsworn Paladin","qty":4}],"sideboard":[{"slug":"song-of-frost","name":"Song of Frost","qty":1},{"slug":"fire-resonance-bauble","name":"Fire Resonance Bauble","qty":1},{"slug":"expel-the-departed","name":"Expel the Departed","qty":2},{"slug":"tidal-sweep","name":"Tidal Sweep","qty":2},{"slug":"stillwater-patrol","name":"Stillwater Patrol","qty":3},{"slug":"snow-fairy","name":"Snow Fairy","qty":1},{"slug":"wind-resonance-bauble","name":"Wind Resonance Bauble","qty":1}]},{"player":29580,"material":[{"slug":"spirit-of-fire","name":"Spirit of Fire","qty":1},{"slug":"rai-spellcrafter","name":"Rai, Spellcrafter","qty":1},{"slug":"rai-archmage","name":"Rai, Archmage","qty":1},{"slug":"rai-storm-seer","name":"Rai, Storm Seer","qty":1},{"slug":"alkahest","name":"Alkahest","qty":1},{"slug":"ducal-seal","name":"Ducal Seal","qty":1},{"slug":"endura-reimagined","name":"Endura, Reimagined","qty":1},{"slug":"endura-scepter-of-ignition","name":"Endura, Scepter of Ignition","qty":1},{"slug":"safeguard-amulet","name":"Safeguard Amulet","qty":1},{"slug":"tome-of-sorcery","name":"Tome of Sorcery","qty":1},{"slug":"storm-tyrants-eye","name":"Storm Tyrant's Eye","qty":1},{"slug":"tome-of-sacred-lightning","name":"Tome of Sacred Lightning","qty":1}],"main":[{"slug":"angel-attendant","name":"Angel Attendant","qty":4},{"slug":"benediction-angel","name":"Benediction Angel","qty":4},{"slug":"careful-study","name":"Careful Study","qty":4},{"slug":"dungeon-guide","name":"Dungeon Guide","qty":4},{"slug":"mnemonic-charm","name":"Mnemonic Charm","qty":2},{"slug":"peaceful-reunion","name":"Peaceful Reunion","qty":2},{"slug":"resolute-stand","name":"Resolute Stand","qty":2},{"slug":"scry-the-skies","name":"Scry the Skies","qty":2},{"slug":"creative-shock","name":"Creative Shock","qty":4},{"slug":"cremation-ritual","name":"Cremation Ritual","qty":4},{"slug":"fireball","name":"Fireball","qty":3},{"slug":"advent-of-the-stormcaller","name":"Advent of the Stormcaller","qty":3},{"slug":"arcane-blast","name":"Arcane Blast","qty":4},{"slug":"arcane-sight","name":"Arcane Sight","qty":3},{"slug":"erratic-bolt","name":"Erratic Bolt","qty":2},{"slug":"power-overwhelming","name":"Power Overwhelming","qty":2},{"slug":"shattering-discharge","name":"Shattering Discharge","qty":4},{"slug":"spellshield-arcane","name":"Spellshield: Arcane","qty":3},{"slug":"surging-search","name":"Surging Search","qty":2},{"slug":"voltaic-sphere","name":"Voltaic Sphere","qty":2}],"sideboard":[{"slug":"nullifying-lantern","name":"Nullifying Lantern","qty":1},{"slug":"peaceful-reunion","name":"Peaceful Reunion","qty":2},{"slug":"resolute-stand","name":"Resolute Stand","qty":2},{"slug":"disintegrate","name":"Disintegrate","qty":2},{"slug":"advent-of-the-stormcaller","name":"Advent of the Stormcaller","qty":1},{"slug":"anger-the-skies","name":"Anger the Skies","qty":2},{"slug":"reversals-polarity","name":"Reversal's Polarity","qty":2},{"slug":"spellshield-arcane","name":"Spellshield: Arcane","qty":1}]},{"player":29859,"material":[{"slug":"mordred-aurelian-regent","name":"Mordred, Aurelian Regent","qty":1},{"slug":"mordred-flawless-blade","name":"Mordred, Flawless Blade","qty":1},{"slug":"mordred-burnished-avenger","name":"Mordred, Burnished Avenger","qty":1},{"slug":"flawless-spirit-of-mordred","name":"Flawless Spirit of Mordred","qty":1},{"slug":"necklace-of-foresight","name":"Necklace of Foresight","qty":1},{"slug":"tome-of-knowledge","name":"Tome of Knowledge","qty":1},{"slug":"eventide-spear","name":"Eventide Spear","qty":1},{"slug":"mirrordepths-blade","name":"Mirrordepth's Blade","qty":1},{"slug":"dummy-trainer","name":"Dummy Trainer","qty":1},{"slug":"rhongomiant-groves-spire","name":"Rhongomiant, Grove's Spire","qty":1},{"slug":"suspicious-concoction","name":"Suspicious Concoction","qty":1},{"slug":"poisoned-dagger","name":"Poisoned Dagger","qty":1}],"main":[{"slug":"lakereaving-chill","name":"Lakereaving Chill","qty":2},{"slug":"frog","name":"Croaking Webfoot","qty":3},{"slug":"dewy-slime","name":"Dewy Slime","qty":4},{"slug":"thronekeeper-bullfrog","name":"Throne-Keeper Bullfrog","qty":4},{"slug":"striking-tides","name":"Striking Tides","qty":4},{"slug":"frostbind","name":"Frostbind","qty":4},{"slug":"dauntless-assault","name":"Dauntless Assault","qty":4},{"slug":"tidal-lock","name":"Tidal Lock","qty":3},{"slug":"wisdoms-reprise","name":"Wisdom's Reprise","qty":4},{"slug":"freezing-hail","name":"Freezing Hail","qty":1},{"slug":"drenching-finish","name":"Drenching Finish","qty":2},{"slug":"fast-cure","name":"Fast Cure","qty":1},{"slug":"gildas-faesworn-monarch","name":"Gildas, Faesworn Monarch","qty":3},{"slug":"resolute-stand","name":"Resolute Stand","qty":1},{"slug":"song-of-frost","name":"Song of Frost","qty":3},{"slug":"tidestone-bovine","name":"Tidestone Bovine","qty":2},{"slug":"dredging-streams","name":"Dredging Streams","qty":4},{"slug":"snow-fairy","name":"Snow Fairy","qty":2},{"slug":"dungeon-guide","name":"Dungeon Guide","qty":3},{"slug":"frostsworn-paladin","name":"Frostsworn Paladin","qty":4},{"slug":"regulus-blitz","name":"Regulus Blitz","qty":2},{"slug":"unyielding-wraithguard","name":"Unyielding Wraithguard","qty":1}],"sideboard":[{"slug":"hypothermia","name":"Hypothermia","qty":1},{"slug":"drenching-finish","name":"Drenching Finish","qty":1},{"slug":"regulus-blitz","name":"Regulus Blitz","qty":2},{"slug":"aqueous-stallion","name":"Aqueous Stallion","qty":1},{"slug":"hoarfrost-spine","name":"Hoarfrost Spine","qty":1},{"slug":"suited-trickery","name":"Suited Trickery","qty":1},{"slug":"unyielding-wraithguard","name":"Unyielding Wraithguard","qty":2},{"slug":"restorative-slash","name":"Restorative Slash","qty":3},{"slug":"freezing-hail","name":"Freezing Hail","qty":2}]},{"player":29935,"material":[{"slug":"dummy-trainer","name":"Dummy Trainer","qty":1},{"slug":"drawn-blade","name":"Drawn Blade","qty":1},{"slug":"flawless-spirit-of-mordred","name":"Flawless Spirit of Mordred","qty":1},{"slug":"mordred-burnished-avenger","name":"Mordred, Burnished Avenger","qty":1},{"slug":"mordred-flawless-blade","name":"Mordred, Flawless Blade","qty":1},{"slug":"tariff-ring","name":"Tariff Ring","qty":1},{"slug":"scepter-of-lumina","name":"Scepter of Lumina","qty":1},{"slug":"mordred-aurelian-regent","name":"Mordred, Aurelian Regent","qty":1},{"slug":"mordred-fated-luminary","name":"Mordred, Fated Luminary","qty":1},{"slug":"rhongomiant-groves-spire","name":"Rhongomiant, Grove's Spire","qty":1},{"slug":"sealed-blade-doa","name":"Sealed Blade","qty":1},{"slug":"teardrop-diadem","name":"Teardrop Diadem","qty":1}],"main":[{"slug":"frostsworn-paladin","name":"Frostsworn Paladin","qty":4},{"slug":"gentle-respite","name":"Gentle Respite","qty":4},{"slug":"dungeon-guide","name":"Dungeon Guide","qty":4},{"slug":"fractal-of-rain","name":"Fractal of Rain","qty":4},{"slug":"fracturize","name":"Fracturize","qty":4},{"slug":"savage-slash","name":"Savage Slash","qty":4},{"slug":"dauntless-assault","name":"Dauntless Assault","qty":3},{"slug":"dredging-streams","name":"Dredging Streams","qty":2},{"slug":"regulus-blitz","name":"Regulus Blitz","qty":2},{"slug":"thronekeeper-bullfrog","name":"Throne-Keeper Bullfrog","qty":3},{"slug":"snow-fairy","name":"Snow Fairy","qty":2},{"slug":"song-of-frost","name":"Song of Frost","qty":2},{"slug":"warrior-of-the-fae-realm","name":"Warrior of the Fae Realm","qty":3},{"slug":"sudden-steel","name":"Sudden Steel","qty":2},{"slug":"freezing-hail","name":"Freezing Hail","qty":2},{"slug":"striking-tides","name":"Striking Tides","qty":3},{"slug":"frostbind","name":"Frostbind","qty":2},{"slug":"deflecting-edge","name":"Deflecting Edge","qty":2},{"slug":"luminescent-slash","name":"Luminescent Slash","qty":3},{"slug":"gildas-faesworn-monarch","name":"Gildas, Faesworn Monarch","qty":3},{"slug":"excalibur-cleansing-light","name":"Excalibur, Cleansing Light","qty":2}],"sideboard":[{"slug":"tidal-sweep","name":"Tidal Sweep","qty":1},{"slug":"regulus-blitz","name":"Regulus Blitz","qty":1},{"slug":"luminescent-slash","name":"Luminescent Slash","qty":1},{"slug":"safeguard-paragon","name":"Safeguard Paragon","qty":3},{"slug":"dredging-streams","name":"Dredging Streams","qty":2},{"slug":"disenchant","name":"Disenchant","qty":3},{"slug":"song-of-frost","name":"Song of Frost","qty":1},{"slug":"thronekeeper-bullfrog","name":"Throne-Keeper Bullfrog","qty":1},{"slug":"snow-fairy","name":"Snow Fairy","qty":1},{"slug":"frostbind","name":"Frostbind","qty":1}]},{"player":30018,"material":[{"slug":"fragmented-spirit-of-fire","name":"Fragmented Spirit of Fire","qty":1},{"slug":"jin-fate-defiant","name":"Jin, Fate Defiant","qty":1},{"slug":"berserker-plate","name":"Berserker Plate","qty":1},{"slug":"safeguard-amulet","name":"Safeguard Amulet","qty":1},{"slug":"executioners-spear","name":"Executioner's Spear","qty":1},{"slug":"jin-zealous-maverick","name":"Jin, Zealous Maverick","qty":1},{"slug":"shuang-ji-of-sacrifice","name":"Shuang Ji of Sacrifice","qty":1},{"slug":"jin-undying-resolve","name":"Jin, Undying Resolve","qty":1},{"slug":"fire-resonance-bauble","name":"Fire Resonance Bauble","qty":1},{"slug":"wind-resonance-bauble","name":"Wind Resonance Bauble","qty":1},{"slug":"sword-of-seeking","name":"Sword of Seeking","qty":1},{"slug":"water-resonance-bauble","name":"Water Resonance Bauble","qty":1}],"main":[{"slug":"savage-swing","name":"Savage Swing","qty":2},{"slug":"cremation-ritual","name":"Cremation Ritual","qty":1},{"slug":"siphoning-stab","name":"Siphoning Stab","qty":1},{"slug":"relentless-outburst","name":"Relentless Outburst","qty":2},{"slug":"mend-flesh","name":"Mend Flesh","qty":2},{"slug":"bloodbond-bladesworn","name":"Bloodbond Bladesworn","qty":2},{"slug":"enrage","name":"Enrage","qty":4},{"slug":"exia-sight","name":"Exia Sight","qty":4},{"slug":"hemorrhaging-rend","name":"Hemorrhaging Rend","qty":2},{"slug":"savage-sunder","name":"Savage Sunder","qty":2},{"slug":"gentle-respite","name":"Gentle Respite","qty":4},{"slug":"flame-rune-swordsman","name":"Flame-Rune Swordsman","qty":4},{"slug":"library-witch","name":"Library Witch","qty":4},{"slug":"dungeon-guide","name":"Dungeon Guide","qty":4},{"slug":"creative-shock","name":"Creative Shock","qty":4},{"slug":"regenerate","name":"Regenerate","qty":4},{"slug":"stalwart-shieldmate","name":"Stalwart Shieldmate","qty":4},{"slug":"hasty-messenger","name":"Hasty Messenger","qty":4},{"slug":"clumsy-apprentice","name":"Clumsy Apprentice","qty":4},{"slug":"incapacitate","name":"Incapacitate","qty":2}],"sideboard":[{"slug":"ignite-fate","name":"Ignite Fate","qty":2},{"slug":"varuckan-acolyte","name":"Varuckan Acolyte","qty":3},{"slug":"bloodbond-bladesworn","name":"Bloodbond Bladesworn","qty":1},{"slug":"reduce-to-ash","name":"Reduce to Ash","qty":2},{"slug":"deflecting-advantage","name":"Deflecting Advantage","qty":1},{"slug":"resolute-stand","name":"Resolute Stand","qty":2},{"slug":"crimson-rupture","name":"Crimson Rupture","qty":1},{"slug":"hemorrhaged-intimidation","name":"Hemorrhaged Intimidation","qty":3}]}]}
